av_clipboard_lib/__init__.py
av_clipboard_lib/av_objects.py
av_clipboard_lib/base85.py
av_clipboard_lib/base_types.py
av_clipboard_lib/clipboard_data.py
av_clipboard_lib/tests.py
av_clipboard_lib/varint.py
av_clipboard_lib-1.9.1.dist-info/LICENSE
av_clipboard_lib-1.9.1.dist-info/METADATA
av_clipboard_lib-1.9.1.dist-info/WHEEL
av_clipboard_lib-1.9.1.dist-info/top_level.txt
av_clipboard_lib-1.9.1.dist-info/RECORD
