Metadata-Version: 2.1
Name: av-clipboard-lib
Version: 1.9.1
Summary: Small ArrowVortex clipboard processing library
Home-page: https://github.com/DeltaEpsilon7787/av-clipboard-lib
Author: DeltaEpsilon7787
Author-email: deltaepsilon7787@gmail.com
License: MIT
Platform: UNKNOWN
Requires-Python: >=3.6
Requires-Dist: attrs
